seizn/__init__.py
seizn/async_client.py
seizn/client.py
seizn/types.py
seizn-0.3.0.dist-info/METADATA
seizn-0.3.0.dist-info/WHEEL
seizn-0.3.0.dist-info/top_level.txt
seizn-0.3.0.dist-info/RECORD
