Metadata-Version: 2.4
Name: seizn
Version: 0.3.0
Summary: Seizn - AI Memory Infrastructure for Developers
Author-email: Seizn Team <support@seizn.dev>
License: MIT
Project-URL: Homepage, https://seizn.dev
Project-URL: Documentation, https://docs.seizn.dev
Project-URL: Repository, https://github.com/seizn/seizn-python
Project-URL: Issues, https://github.com/seizn/seizn-python/issues
Keywords: ai,memory,llm,rag,embeddings,vector-search
Classifier: Development Status :: 4 - Beta
Classifier: Intended Audience :: Developers
Classifier: License :: OSI Approved :: MIT License
Classifier: Programming Language :: Python :: 3
Classifier: Programming Language :: Python :: 3.8
Classifier: Programming Language :: Python :: 3.9
Classifier: Programming Language :: Python :: 3.10
Classifier: Programming Language :: Python :: 3.11
Classifier: Programming Language :: Python :: 3.12
Classifier: Topic :: Software Development :: Libraries :: Python Modules
Classifier: Topic :: Scientific/Engineering :: Artificial Intelligence
Requires-Python: >=3.8
Requires-Dist: httpx>=0.24.0
Provides-Extra: dev
Requires-Dist: pytest>=7.0; extra == "dev"
Requires-Dist: pytest-asyncio>=0.21; extra == "dev"
Requires-Dist: black>=23.0; extra == "dev"
Requires-Dist: mypy>=1.0; extra == "dev"
Requires-Dist: ruff>=0.1; extra == "dev"
